keychestbot/__init__.py
keychestbot/__main__.py
keychestbot/bot.py
keychestbot/setup.cfg
keychestbot-0.1.dist-info/METADATA
keychestbot-0.1.dist-info/RECORD
keychestbot-0.1.dist-info/WHEEL
keychestbot-0.1.dist-info/entry_points.txt
keychestbot-0.1.dist-info/top_level.txt
