Metadata-Version: 2.1
Name: keychestbot
Version: 0.1
Summary: Client bot for KeyChest monitoring service
Home-page: http://keychest.net
Author: Radical Prime Limited
Author-email: support@radicalprime.com
License: MIT License
Requires-Dist: requests (>=2.11.1)
Requires-Dist: coloredlogs (>=9.0)
Requires-Dist: setuptools (>=39.0)
